easchersim/__init__.py
easchersim/_version.py
easchersim/atmosphere.py
easchersim/cher_func.py
easchersim/constants.py
easchersim/eas_cher_sim.py
easchersim/electron_func.py
easchersim/fit_func.py
easchersim/geometry.py
easchersim/io_func.py
easchersim/plot.py
easchersim/spatial_cherenkov_profile.py
easchersim/data/Example_CORSIKA_proton_1e17eV.long
easchersim/data/__init__.py
easchersim/data/alpha_values_typical_atmosphere_updated.txt
easchersim/data/default_conf.ini
easchersim-1.2.0.dist-info/LICENSE
easchersim-1.2.0.dist-info/METADATA
easchersim-1.2.0.dist-info/WHEEL
easchersim-1.2.0.dist-info/entry_points.txt
easchersim-1.2.0.dist-info/top_level.txt
easchersim-1.2.0.dist-info/RECORD
