Metadata-Version: 2.1
Name: easchersim
Version: 1.2.0
Summary: A Simulator for Cherenkov photon production and atmopheric transport for Extensive Air Showers
Home-page: https://gitlab.com/c4341/easchersim
Author: Austin Cummings, Johannes Eser
Author-email: alc6658@psu.edu, jeser@uchicago.edu
License: BSD-3-Clause-Clear
Keywords: Extensive Air Shower,Cherenkov,neutrinos,Simulation
Classifier: Intended Audience :: Science/Research
Classifier: Programming Language :: Python :: 3
Classifier: Programming Language :: Python :: 3 :: Only
Classifier: Programming Language :: Python :: 3.8
Classifier: Programming Language :: Python :: 3.9
Classifier: Programming Language :: Python :: 3.10
License-File: LICENSE
Requires-Dist: matplotlib
Requires-Dist: numpy
Requires-Dist: scipy
Requires-Dist: importlib-resources
Requires-Dist: matplotlib-label-lines
Requires-Dist: rich
